README.rst
bootstrap.py
buildout.cfg
develop.cfg
setup.py
collective/__init__.py
collective.formtoy.egg-info/PKG-INFO
collective.formtoy.egg-info/SOURCES.txt
collective.formtoy.egg-info/dependency_links.txt
collective.formtoy.egg-info/entry_points.txt
collective.formtoy.egg-info/namespace_packages.txt
collective.formtoy.egg-info/not-zip-safe
collective.formtoy.egg-info/requires.txt
collective.formtoy.egg-info/top_level.txt
collective/formtoy/__init__.py
collective/formtoy/configure.zcml
collective/formtoy/tests.py
collective/formtoy/browser/__init__.py
collective/formtoy/browser/configure.zcml
collective/formtoy/browser/formtoy.pt
collective/formtoy/browser/formtoy.py
collective/formtoy/profiles/default/controlpanel.xml
docs/HISTORY.txt
docs/INSTALL.txt
docs/LICENSE.GPL
docs/LICENSE.txt