Metadata-Version: 1.0
Name: collective.formtoy
Version: 0.3.0
Summary: A tool to mock up ad hoc forms in Plone
Home-page: http://svn.plone.org/svn/collective/
Author: Alex Clark
Author-email: aclark@aclark.net
License: GPL
Keywords: html form marshall zope
Platform: UNKNOWN
Classifier: Framework :: Plone
Classifier: Programming Language :: Python
